{
  "generated_at": "2026-04-25T13:29:54.746Z",
  "totals": {
    "ballots": 3074,
    "matched_to_aidoge": 97,
    "unmatched": 2977,
    "councils_with_full_coverage": 6,
    "councils_with_partial_coverage": 1,
    "councils_with_zero_coverage": 152
  },
  "council_coverage": {
    "": {
      "matched": 0,
      "total": 16,
      "council_name": "Senedd Cymru",
      "tier": "senedd"
    },
    "adur": {
      "matched": 0,
      "total": 14,
      "council_name": "Adur",
      "tier": "local"
    },
    "barking-and-dagenham": {
      "matched": 0,
      "total": 19,
      "council_name": "Barking and Dagenham",
      "tier": "local"
    },
    "barnet": {
      "matched": 0,
      "total": 24,
      "council_name": "Barnet",
      "tier": "local"
    },
    "barnsley": {
      "matched": 0,
      "total": 21,
      "council_name": "Barnsley",
      "tier": "local"
    },
    "basildon": {
      "matched": 0,
      "total": 14,
      "council_name": "Basildon",
      "tier": "local"
    },
    "basingstoke-and-deane": {
      "matched": 0,
      "total": 18,
      "council_name": "Basingstoke and Deane",
      "tier": "local"
    },
    "bexley": {
      "matched": 0,
      "total": 17,
      "council_name": "Bexley",
      "tier": "local"
    },
    "birmingham": {
      "matched": 0,
      "total": 69,
      "council_name": "Birmingham",
      "tier": "local"
    },
    "blackburn-with-darwen": {
      "matched": 17,
      "total": 17,
      "council_name": "Blackburn with Darwen",
      "tier": "local"
    },
    "bolton": {
      "matched": 0,
      "total": 20,
      "council_name": "Bolton",
      "tier": "local"
    },
    "bradford": {
      "matched": 0,
      "total": 30,
      "council_name": "Bradford",
      "tier": "local"
    },
    "brent": {
      "matched": 0,
      "total": 22,
      "council_name": "Brent",
      "tier": "local"
    },
    "brentwood": {
      "matched": 0,
      "total": 13,
      "council_name": "Brentwood",
      "tier": "local"
    },
    "bromley": {
      "matched": 0,
      "total": 22,
      "council_name": "Bromley",
      "tier": "local"
    },
    "broxbourne": {
      "matched": 0,
      "total": 10,
      "council_name": "Broxbourne",
      "tier": "local"
    },
    "burnley": {
      "matched": 15,
      "total": 15,
      "council_name": "Burnley",
      "tier": "local"
    },
    "bury": {
      "matched": 0,
      "total": 17,
      "council_name": "Bury",
      "tier": "local"
    },
    "c": {
      "matched": 0,
      "total": 73,
      "council_name": "Scottish Parliament elections (Constituencies)",
      "tier": "holyrood"
    },
    "calderdale": {
      "matched": 0,
      "total": 18,
      "council_name": "Calderdale",
      "tier": "local"
    },
    "cambridge": {
      "matched": 0,
      "total": 14,
      "council_name": "Cambridge",
      "tier": "local"
    },
    "camden": {
      "matched": 0,
      "total": 20,
      "council_name": "Camden",
      "tier": "local"
    },
    "cannock-chase": {
      "matched": 0,
      "total": 12,
      "council_name": "Cannock Chase",
      "tier": "local"
    },
    "chelmsford": {
      "matched": 0,
      "total": 1,
      "council_name": "Chelmsford",
      "tier": "local"
    },
    "cheltenham": {
      "matched": 0,
      "total": 20,
      "council_name": "Cheltenham",
      "tier": "local"
    },
    "cherwell": {
      "matched": 0,
      "total": 16,
      "council_name": "Cherwell",
      "tier": "local"
    },
    "chesterfield": {
      "matched": 0,
      "total": 1,
      "council_name": "Chesterfield",
      "tier": "local"
    },
    "chorley": {
      "matched": 14,
      "total": 14,
      "council_name": "Chorley",
      "tier": "local"
    },
    "city-of-lincoln": {
      "matched": 0,
      "total": 11,
      "council_name": "City of Lincoln",
      "tier": "local"
    },
    "colchester": {
      "matched": 0,
      "total": 17,
      "council_name": "Colchester",
      "tier": "local"
    },
    "coventry": {
      "matched": 0,
      "total": 18,
      "council_name": "Coventry",
      "tier": "local"
    },
    "crawley": {
      "matched": 0,
      "total": 12,
      "council_name": "Crawley",
      "tier": "local"
    },
    "croydon": {
      "matched": 0,
      "total": 29,
      "council_name": "Croydon",
      "tier": "local"
    },
    "dudley": {
      "matched": 0,
      "total": 24,
      "council_name": "Dudley",
      "tier": "local"
    },
    "ealing": {
      "matched": 0,
      "total": 24,
      "council_name": "Ealing",
      "tier": "local"
    },
    "east-hertfordshire": {
      "matched": 0,
      "total": 1,
      "council_name": "East Hertfordshire",
      "tier": "local"
    },
    "east-surrey": {
      "matched": 0,
      "total": 36,
      "council_name": "East Surrey",
      "tier": "local"
    },
    "east-sussex": {
      "matched": 0,
      "total": 50,
      "council_name": "East Sussex",
      "tier": "local"
    },
    "eastleigh": {
      "matched": 0,
      "total": 14,
      "council_name": "Eastleigh",
      "tier": "local"
    },
    "enfield": {
      "matched": 0,
      "total": 25,
      "council_name": "Enfield",
      "tier": "local"
    },
    "epping-forest": {
      "matched": 0,
      "total": 18,
      "council_name": "Epping Forest",
      "tier": "local"
    },
    "essex": {
      "matched": 0,
      "total": 78,
      "council_name": "Essex",
      "tier": "local"
    },
    "exeter": {
      "matched": 0,
      "total": 13,
      "council_name": "Exeter",
      "tier": "local"
    },
    "fareham": {
      "matched": 0,
      "total": 16,
      "council_name": "Fareham",
      "tier": "local"
    },
    "gateshead": {
      "matched": 0,
      "total": 22,
      "council_name": "Gateshead",
      "tier": "local"
    },
    "gloucestershire": {
      "matched": 0,
      "total": 1,
      "council_name": "Gloucestershire",
      "tier": "local"
    },
    "gosport": {
      "matched": 0,
      "total": 14,
      "council_name": "Gosport",
      "tier": "local"
    },
    "great-yarmouth": {
      "matched": 0,
      "total": 1,
      "council_name": "Great Yarmouth",
      "tier": "local"
    },
    "greenwich": {
      "matched": 0,
      "total": 23,
      "council_name": "Greenwich",
      "tier": "local"
    },
    "guildford": {
      "matched": 0,
      "total": 1,
      "council_name": "Guildford",
      "tier": "local"
    },
    "hackney": {
      "matched": 0,
      "total": 22,
      "council_name": "London Borough of Hackney",
      "tier": "local"
    },
    "halton": {
      "matched": 0,
      "total": 18,
      "council_name": "Halton",
      "tier": "local"
    },
    "hammersmith-and-fulham": {
      "matched": 0,
      "total": 21,
      "council_name": "Hammersmith and Fulham",
      "tier": "local"
    },
    "hampshire": {
      "matched": 0,
      "total": 76,
      "council_name": "Hampshire",
      "tier": "local"
    },
    "haringey": {
      "matched": 0,
      "total": 21,
      "council_name": "Haringey",
      "tier": "local"
    },
    "harlow": {
      "matched": 0,
      "total": 11,
      "council_name": "Harlow",
      "tier": "local"
    },
    "harrow": {
      "matched": 0,
      "total": 22,
      "council_name": "Harrow",
      "tier": "local"
    },
    "hart": {
      "matched": 0,
      "total": 11,
      "council_name": "Hart",
      "tier": "local"
    },
    "hartlepool": {
      "matched": 0,
      "total": 12,
      "council_name": "Hartlepool",
      "tier": "local"
    },
    "hastings": {
      "matched": 0,
      "total": 16,
      "council_name": "Hastings",
      "tier": "local"
    },
    "havant": {
      "matched": 0,
      "total": 12,
      "council_name": "Havant",
      "tier": "local"
    },
    "havering": {
      "matched": 0,
      "total": 20,
      "council_name": "Havering",
      "tier": "local"
    },
    "hertfordshire": {
      "matched": 0,
      "total": 1,
      "council_name": "Hertfordshire",
      "tier": "local"
    },
    "hertsmere": {
      "matched": 0,
      "total": 1,
      "council_name": "Hertsmere",
      "tier": "local"
    },
    "hillingdon": {
      "matched": 0,
      "total": 21,
      "council_name": "Hillingdon",
      "tier": "local"
    },
    "horsham": {
      "matched": 0,
      "total": 1,
      "council_name": "Horsham",
      "tier": "local"
    },
    "hounslow": {
      "matched": 0,
      "total": 22,
      "council_name": "Hounslow",
      "tier": "local"
    },
    "huntingdonshire": {
      "matched": 0,
      "total": 26,
      "council_name": "Huntingdonshire",
      "tier": "local"
    },
    "hyndburn": {
      "matched": 11,
      "total": 11,
      "council_name": "Hyndburn",
      "tier": "local"
    },
    "ipswich": {
      "matched": 0,
      "total": 16,
      "council_name": "Ipswich",
      "tier": "local"
    },
    "isle-of-wight": {
      "matched": 0,
      "total": 39,
      "council_name": "Isle of Wight",
      "tier": "local"
    },
    "islington": {
      "matched": 0,
      "total": 17,
      "council_name": "Islington",
      "tier": "local"
    },
    "kensington-and-chelsea": {
      "matched": 0,
      "total": 18,
      "council_name": "Kensington and Chelsea",
      "tier": "local"
    },
    "kingston-upon-hull": {
      "matched": 0,
      "total": 19,
      "council_name": "Kingston upon Hull",
      "tier": "local"
    },
    "kingston-upon-thames": {
      "matched": 0,
      "total": 19,
      "council_name": "Kingston upon Thames",
      "tier": "local"
    },
    "kirklees": {
      "matched": 0,
      "total": 23,
      "council_name": "Kirklees",
      "tier": "local"
    },
    "knowsley": {
      "matched": 0,
      "total": 15,
      "council_name": "Knowsley",
      "tier": "local"
    },
    "lambeth": {
      "matched": 0,
      "total": 25,
      "council_name": "Lambeth",
      "tier": "local"
    },
    "leeds": {
      "matched": 0,
      "total": 33,
      "council_name": "Leeds",
      "tier": "local"
    },
    "lewes": {
      "matched": 0,
      "total": 1,
      "council_name": "Lewes",
      "tier": "local"
    },
    "lewisham": {
      "matched": 0,
      "total": 20,
      "council_name": "London Borough of Lewisham",
      "tier": "local"
    },
    "manchester": {
      "matched": 0,
      "total": 32,
      "council_name": "Manchester",
      "tier": "local"
    },
    "merton": {
      "matched": 0,
      "total": 20,
      "council_name": "Merton",
      "tier": "local"
    },
    "mid-sussex": {
      "matched": 0,
      "total": 1,
      "council_name": "Mid Sussex",
      "tier": "local"
    },
    "milton-keynes": {
      "matched": 0,
      "total": 21,
      "council_name": "Milton Keynes",
      "tier": "local"
    },
    "newcastle-under-lyme": {
      "matched": 0,
      "total": 21,
      "council_name": "Newcastle-under-Lyme",
      "tier": "local"
    },
    "newcastle-upon-tyne": {
      "matched": 0,
      "total": 26,
      "council_name": "Newcastle upon Tyne",
      "tier": "local"
    },
    "newham": {
      "matched": 0,
      "total": 25,
      "council_name": "London Borough of Newham",
      "tier": "local"
    },
    "newport": {
      "matched": 0,
      "total": 1,
      "council_name": "Newport",
      "tier": "local"
    },
    "norfolk": {
      "matched": 0,
      "total": 84,
      "council_name": "Norfolk",
      "tier": "local"
    },
    "north-east-lincolnshire": {
      "matched": 0,
      "total": 15,
      "council_name": "North East Lincolnshire",
      "tier": "local"
    },
    "north-tyneside": {
      "matched": 0,
      "total": 20,
      "council_name": "North Tyneside Council",
      "tier": "local"
    },
    "norwich": {
      "matched": 0,
      "total": 13,
      "council_name": "Norwich",
      "tier": "local"
    },
    "nuneaton-and-bedworth": {
      "matched": 0,
      "total": 19,
      "council_name": "Nuneaton and Bedworth",
      "tier": "local"
    },
    "oldham": {
      "matched": 0,
      "total": 20,
      "council_name": "Oldham",
      "tier": "local"
    },
    "oxford": {
      "matched": 0,
      "total": 24,
      "council_name": "Oxford",
      "tier": "local"
    },
    "pendle": {
      "matched": 10,
      "total": 10,
      "council_name": "Pendle",
      "tier": "local"
    },
    "peterborough": {
      "matched": 0,
      "total": 18,
      "council_name": "Peterborough",
      "tier": "local"
    },
    "plymouth": {
      "matched": 0,
      "total": 19,
      "council_name": "Plymouth",
      "tier": "local"
    },
    "portsmouth": {
      "matched": 0,
      "total": 14,
      "council_name": "Portsmouth",
      "tier": "local"
    },
    "powys": {
      "matched": 0,
      "total": 1,
      "council_name": "Powys",
      "tier": "local"
    },
    "preston": {
      "matched": 16,
      "total": 16,
      "council_name": "Preston",
      "tier": "local"
    },
    "r": {
      "matched": 0,
      "total": 8,
      "council_name": "Scottish Parliament elections (Regions)",
      "tier": "holyrood"
    },
    "reading": {
      "matched": 0,
      "total": 16,
      "council_name": "Reading",
      "tier": "local"
    },
    "redbridge": {
      "matched": 0,
      "total": 22,
      "council_name": "Redbridge",
      "tier": "local"
    },
    "redditch": {
      "matched": 0,
      "total": 9,
      "council_name": "Redditch",
      "tier": "local"
    },
    "reigate-and-banstead": {
      "matched": 0,
      "total": 1,
      "council_name": "Reigate and Banstead",
      "tier": "local"
    },
    "richmond-upon-thames": {
      "matched": 0,
      "total": 18,
      "council_name": "Richmond upon Thames",
      "tier": "local"
    },
    "rochdale": {
      "matched": 0,
      "total": 20,
      "council_name": "Rochdale",
      "tier": "local"
    },
    "rochford": {
      "matched": 0,
      "total": 13,
      "council_name": "Rochford",
      "tier": "local"
    },
    "rother": {
      "matched": 0,
      "total": 1,
      "council_name": "Rother",
      "tier": "local"
    },
    "rugby": {
      "matched": 0,
      "total": 14,
      "council_name": "Rugby",
      "tier": "local"
    },
    "rushmoor": {
      "matched": 0,
      "total": 13,
      "council_name": "Rushmoor",
      "tier": "local"
    },
    "salford": {
      "matched": 0,
      "total": 20,
      "council_name": "Salford City Council",
      "tier": "local"
    },
    "sandwell": {
      "matched": 0,
      "total": 24,
      "council_name": "Sandwell",
      "tier": "local"
    },
    "sefton": {
      "matched": 0,
      "total": 22,
      "council_name": "Sefton",
      "tier": "local"
    },
    "sheffield": {
      "matched": 0,
      "total": 28,
      "council_name": "Sheffield",
      "tier": "local"
    },
    "solihull": {
      "matched": 0,
      "total": 17,
      "council_name": "Solihull",
      "tier": "local"
    },
    "somerset": {
      "matched": 0,
      "total": 1,
      "council_name": "Somerset",
      "tier": "local"
    },
    "south-cambridgeshire": {
      "matched": 0,
      "total": 26,
      "council_name": "South Cambridgeshire",
      "tier": "local"
    },
    "south-tyneside": {
      "matched": 0,
      "total": 18,
      "council_name": "South Tyneside",
      "tier": "local"
    },
    "southampton": {
      "matched": 0,
      "total": 17,
      "council_name": "Southampton",
      "tier": "local"
    },
    "southend-on-sea": {
      "matched": 0,
      "total": 17,
      "council_name": "Southend-on-Sea",
      "tier": "local"
    },
    "southwark": {
      "matched": 0,
      "total": 23,
      "council_name": "Southwark",
      "tier": "local"
    },
    "st-albans": {
      "matched": 0,
      "total": 20,
      "council_name": "St Albans",
      "tier": "local"
    },
    "st-helens": {
      "matched": 0,
      "total": 18,
      "council_name": "St. Helens",
      "tier": "local"
    },
    "stevenage": {
      "matched": 0,
      "total": 13,
      "council_name": "Stevenage",
      "tier": "local"
    },
    "stockport": {
      "matched": 0,
      "total": 21,
      "council_name": "Stockport",
      "tier": "local"
    },
    "stratford-on-avon": {
      "matched": 0,
      "total": 1,
      "council_name": "Stratford-on-Avon",
      "tier": "local"
    },
    "suffolk": {
      "matched": 0,
      "total": 69,
      "council_name": "Suffolk",
      "tier": "local"
    },
    "sunderland": {
      "matched": 0,
      "total": 25,
      "council_name": "Sunderland",
      "tier": "local"
    },
    "surrey": {
      "matched": 0,
      "total": 1,
      "council_name": "Surrey",
      "tier": "local"
    },
    "sutton": {
      "matched": 0,
      "total": 20,
      "council_name": "Sutton",
      "tier": "local"
    },
    "swindon": {
      "matched": 0,
      "total": 25,
      "council_name": "Swindon",
      "tier": "local"
    },
    "tameside": {
      "matched": 0,
      "total": 19,
      "council_name": "Tameside",
      "tier": "local"
    },
    "tamworth": {
      "matched": 0,
      "total": 10,
      "council_name": "Tamworth",
      "tier": "local"
    },
    "three-rivers": {
      "matched": 0,
      "total": 13,
      "council_name": "Three Rivers",
      "tier": "local"
    },
    "thurrock": {
      "matched": 0,
      "total": 20,
      "council_name": "Thurrock",
      "tier": "local"
    },
    "tower-hamlets": {
      "matched": 0,
      "total": 21,
      "council_name": "London Borough of Tower Hamlets",
      "tier": "local"
    },
    "trafford": {
      "matched": 0,
      "total": 21,
      "council_name": "Trafford",
      "tier": "local"
    },
    "tunbridge-wells": {
      "matched": 0,
      "total": 13,
      "council_name": "Tunbridge Wells",
      "tier": "local"
    },
    "wakefield": {
      "matched": 0,
      "total": 21,
      "council_name": "Wakefield",
      "tier": "local"
    },
    "walsall": {
      "matched": 0,
      "total": 20,
      "council_name": "Walsall",
      "tier": "local"
    },
    "waltham-forest": {
      "matched": 0,
      "total": 22,
      "council_name": "Waltham Forest",
      "tier": "local"
    },
    "wandsworth": {
      "matched": 0,
      "total": 22,
      "council_name": "Wandsworth",
      "tier": "local"
    },
    "watford": {
      "matched": 0,
      "total": 13,
      "council_name": "Watford Borough Council",
      "tier": "local"
    },
    "welwyn-hatfield": {
      "matched": 0,
      "total": 16,
      "council_name": "Welwyn Hatfield",
      "tier": "local"
    },
    "west-lancashire": {
      "matched": 14,
      "total": 15,
      "council_name": "West Lancashire",
      "tier": "local"
    },
    "west-northamptonshire": {
      "matched": 0,
      "total": 1,
      "council_name": "West Northamptonshire",
      "tier": "local"
    },
    "west-oxfordshire": {
      "matched": 0,
      "total": 16,
      "council_name": "West Oxfordshire",
      "tier": "local"
    },
    "west-suffolk": {
      "matched": 0,
      "total": 1,
      "council_name": "West Suffolk",
      "tier": "local"
    },
    "west-surrey": {
      "matched": 0,
      "total": 45,
      "council_name": "West Surrey",
      "tier": "local"
    },
    "west-sussex": {
      "matched": 0,
      "total": 70,
      "council_name": "West Sussex",
      "tier": "local"
    },
    "westminster": {
      "matched": 0,
      "total": 18,
      "council_name": "Westminster",
      "tier": "local"
    },
    "wigan": {
      "matched": 0,
      "total": 25,
      "council_name": "Wigan",
      "tier": "local"
    },
    "winchester": {
      "matched": 0,
      "total": 15,
      "council_name": "Winchester",
      "tier": "local"
    },
    "wokingham": {
      "matched": 0,
      "total": 18,
      "council_name": "Wokingham",
      "tier": "local"
    },
    "wolverhampton": {
      "matched": 0,
      "total": 20,
      "council_name": "Wolverhampton",
      "tier": "local"
    },
    "worthing": {
      "matched": 0,
      "total": 13,
      "council_name": "Worthing",
      "tier": "local"
    }
  },
  "doge_wards_indexed": 298
}