{
  "generatedAt": "2026-04-14T14:41:33.638Z",
  "source": "ONS Births Linked 2024 (Tables 5 & 8) + Census 2021 custom dataset",
  "methodology": "Census-derived CWRs computed as Children(0-4) / Women(15-44) per ethnic group per LA. The HP model uses these directly. Empirical TFRs computed from ONS 2024 annual births / Census 2021 women(15-44) × 30. ASFRs from Table 8 age band marginals. IMD fertility gradient from Table 8 deprivation marginals.",
  "censusCWR": {
    "WBI": 0.2842,
    "WIR": 0.1026,
    "WGT": 0.426,
    "WRO": 0.2211,
    "WHO": 0.1532,
    "MWA": 0.7702,
    "MWF": 0.7643,
    "MWC": 0.5356,
    "MOM": 0.5767,
    "IND": 0.2512,
    "PAK": 0.3587,
    "BAN": 0.3277,
    "CHI": 0.1189,
    "OAS": 0.2295,
    "BAF": 0.2612,
    "BCA": 0.1722,
    "OBL": 0.6663,
    "ARB": 0.336,
    "OOT": 0.241
  },
  "empiricalTFR": {
    "BAN": 2.27,
    "IND": 2.17,
    "PAK": 2.52,
    "OAS": 2.62,
    "BAF": 2.42,
    "BCA": 1.13,
    "OBL": 2.58,
    "MIX": 3.13,
    "OOT": 2,
    "WBI": 1.31,
    "WHO": 1.58
  },
  "empiricalTFRDetail": {
    "BAN": {
      "births": 12787,
      "women": 169308,
      "tfr": 2.27,
      "onsLabel": "Bangladeshi"
    },
    "IND": {
      "births": 31848,
      "women": 440069,
      "tfr": 2.17,
      "onsLabel": "Indian"
    },
    "PAK": {
      "births": 32971,
      "women": 392195,
      "tfr": 2.52,
      "onsLabel": "Pakistani"
    },
    "OAS": {
      "births": 21616,
      "women": 247727,
      "tfr": 2.62,
      "onsLabel": "Any other Asian background"
    },
    "BAF": {
      "births": 31372,
      "women": 388482,
      "tfr": 2.42,
      "onsLabel": "Black African"
    },
    "BCA": {
      "births": 4799,
      "women": 127180,
      "tfr": 1.13,
      "onsLabel": "Black Caribbean"
    },
    "OBL": {
      "births": 4478,
      "women": 52132,
      "tfr": 2.58,
      "onsLabel": "Any other Black background"
    },
    "MIX": {
      "births": 39844,
      "women": 381318,
      "tfr": 3.13,
      "onsLabel": "Mixed/multiple ethnic groups"
    },
    "OOT": {
      "births": 14960,
      "women": 224664,
      "tfr": 2,
      "onsLabel": "Any other ethnic group"
    },
    "WBI": {
      "births": 304244,
      "women": 6969688,
      "tfr": 1.31,
      "onsLabel": "White British"
    },
    "WHO": {
      "births": 59275,
      "women": 1124781,
      "tfr": 1.58,
      "onsLabel": "Any other White background"
    }
  },
  "sixGroupTFR": {
    "white_british": 1.31,
    "white_other": 1.43,
    "asian": 2.15,
    "black": 2.15,
    "mixed": 3.13,
    "other": 1.48
  },
  "nationalASFR": {
    "15-19": 0.0081,
    "20-24": 0.0377,
    "25-29": 0.0773,
    "30-34": 0.098,
    "35-39": 0.0618,
    "40-44": 0.0152,
    "45-49": 0.0014
  },
  "nationalTFR": 1.5,
  "totalBirths2024": 567412,
  "fertilityByIMD": {
    "Decile 1": {
      "births": 75561,
      "pctOfBirths": 13.3,
      "decile": 1
    },
    "Decile 2": {
      "births": 68961,
      "pctOfBirths": 12.2,
      "decile": 2
    },
    "Decile 3": {
      "births": 65431,
      "pctOfBirths": 11.5,
      "decile": 3
    },
    "Decile 4": {
      "births": 60347,
      "pctOfBirths": 10.6,
      "decile": 4
    },
    "Decile 5": {
      "births": 56383,
      "pctOfBirths": 9.9,
      "decile": 5
    },
    "Decile 6": {
      "births": 54179,
      "pctOfBirths": 9.5,
      "decile": 6
    },
    "Decile 7": {
      "births": 50458,
      "pctOfBirths": 8.9,
      "decile": 7
    },
    "Decile 8": {
      "births": 48924,
      "pctOfBirths": 8.6,
      "decile": 8
    },
    "Decile 9": {
      "births": 46009,
      "pctOfBirths": 8.1,
      "decile": 9
    },
    "Decile 10": {
      "births": 41207,
      "pctOfBirths": 7.3,
      "decile": 10
    }
  },
  "deprivationGradient": {
    "mostDeprivedQuintileBirths": 144522,
    "leastDeprivedQuintileBirths": 87216,
    "ratio": 1.66,
    "insight": "Women in the most deprived quintile have 1.66x more births than the least deprived. This deprivation gradient is a major driver of apparent ethnic fertility differentials — Pakistani and Bangladeshi populations are concentrated in deprived areas."
  },
  "regionalBirthShares": {
    "NORTH EAST": {
      "totalBirths": 24217,
      "wbiPct": 77.3,
      "nonWbiPct": 22.7
    },
    "NORTH WEST": {
      "totalBirths": 74631,
      "wbiPct": 62.3,
      "nonWbiPct": 37.7
    },
    "YORKSHIRE AND THE HUMBER": {
      "totalBirths": 54476,
      "wbiPct": 61.7,
      "nonWbiPct": 38.3
    },
    "EAST MIDLANDS": {
      "totalBirths": 45475,
      "wbiPct": 60.4,
      "nonWbiPct": 39.6
    },
    "WEST MIDLANDS": {
      "totalBirths": 64182,
      "wbiPct": 48.9,
      "nonWbiPct": 51.1
    },
    "EAST OF ENGLAND": {
      "totalBirths": 63099,
      "wbiPct": 56.2,
      "nonWbiPct": 43.8
    },
    "LONDON": {
      "totalBirths": 106095,
      "wbiPct": 20.7,
      "nonWbiPct": 79.3
    },
    "SOUTH EAST": {
      "totalBirths": 88135,
      "wbiPct": 61,
      "nonWbiPct": 39
    },
    "SOUTH WEST": {
      "totalBirths": 47150,
      "wbiPct": 75,
      "nonWbiPct": 25
    }
  },
  "onsBirths2024ByEthnicity": {
    "Bangladeshi": 12787,
    "Indian": 31848,
    "Pakistani": 32971,
    "Any other Asian background": 21616,
    "Black African": 31372,
    "Black Caribbean": 4799,
    "Any other Black background": 4478,
    "Mixed/multiple ethnic groups": 39844,
    "Any other ethnic group": 14960,
    "White British": 304244,
    "Any other White background": 59275,
    "Not stated": 9266
  },
  "note": "The v6.0 HP model uses Census-derived CWRs per LA per ethnic group — NOT hardcoded TFRs. These empirical ONS 2024 rates serve as independent validation and calibration data. Table 8 provides ethnicity, IMD, and age as separate marginals (not a full ethnicity × IMD × age cross-tab). The full cross-tab would be needed to compute ethnic-specific ASFRs by deprivation — this requires an ONS ad-hoc request or indirect estimation."
}