{
  "snapshot": {
    "snapshot_id": "dc-ballots-2026-05-07-f2d10be9b458",
    "source_name": "Democracy Club Candidates API",
    "source_url": "https://candidates.democracyclub.org.uk/api/next/ballots/?election_date=2026-05-07",
    "retrieved_at": "2026-04-25T13:18:53.287Z",
    "licence": "Democracy Club election data is published under CC0 1.0 for raw fields; party metadata sourced from Electoral Commission (OGL).",
    "sha256": "f2d10be9b4586f99c9ca12ceeb3ff4e7188528533f5bc1763103201e3ff78b3a",
    "quality_status": "imported_quarantined",
    "review_notes": "Bulk DC API fetch. Verify candidate locks + cancellations + SoPN URLs before any per-contest publication."
  },
  "election_group": {
    "election_id": "local.portsmouth.2026-05-07",
    "name": "Portsmouth local election",
    "classification": {
      "tier": "local",
      "model_family_hint": "local_fptp"
    }
  },
  "ballots": [
    {
      "ballot_paper_id": "local.portsmouth.baffins.2026-05-07",
      "post": {
        "id": "gss:E05002441",
        "label": "Baffins",
        "slug": "baffins",
        "created": "2016-03-18T17:09:45.884740Z",
        "last_updated": "2021-10-28T15:44:33.991444+01:00"
      },
      "winner_count": 1,
      "cancelled": false,
      "candidates_locked": true,
      "sopn_url": "https://candidates.democracyclub.org.uk/media/official_documents/local.portsmouth.baffins.2026-05-07/sopn/2026-04-10T09%3A32%3A00.438640%2B00%3A00/sopn-local.portsmouth.baffins.2026-05-07.pdf",
      "sopn_source_url": "https://www.portsmouth.gov.uk/wp-content/uploads/2026/04/Statement-of-Persons-Nominated-2026-City-Council-Elections-accessible-aa.pdf",
      "candidates": [
        {
          "person_id": 131056,
          "name": "Jemma Louise ARTEMIS",
          "party_name": "Labour Party",
          "party_ec_id": "PP53",
          "party_description_text": null,
          "party_list_position": null,
          "deselected": false,
          "elected": null
        },
        {
          "person_id": 88981,
          "name": "Abdul KADIR",
          "party_name": "Liberal Democrats",
          "party_ec_id": "PP90",
          "party_description_text": "Liberal Democrat",
          "party_list_position": null,
          "deselected": false,
          "elected": null
        },
        {
          "person_id": 123550,
          "name": "Darren John SEARLEY",
          "party_name": "Reform UK",
          "party_ec_id": "PP7931",
          "party_description_text": null,
          "party_list_position": null,
          "deselected": false,
          "elected": null
        },
        {
          "person_id": 109969,
          "name": "Dave Giovanni LEME DA SILVA",
          "party_name": "Conservative and Unionist Party",
          "party_ec_id": "PP52",
          "party_description_text": "Local Conservatives",
          "party_list_position": null,
          "deselected": false,
          "elected": null
        },
        {
          "person_id": 131057,
          "name": "David Anthony SIMPSON",
          "party_name": "Green Party",
          "party_ec_id": "PP63",
          "party_description_text": null,
          "party_list_position": null,
          "deselected": false,
          "elected": null
        }
      ]
    },
    {
      "ballot_paper_id": "local.portsmouth.central-southsea.2026-05-07",
      "post": {
        "id": "gss:E05002442",
        "label": "Central Southsea",
        "slug": "central-southsea",
        "created": "2016-03-18T17:09:45.900819Z",
        "last_updated": "2021-10-28T15:44:34.080436+01:00"
      },
      "winner_count": 1,
      "cancelled": false,
      "candidates_locked": true,
      "sopn_url": "https://candidates.democracyclub.org.uk/media/official_documents/local.portsmouth.central-southsea.2026-05-07/sopn/2026-04-10T09%3A32%3A00.996167%2B00%3A00/sopn-local.portsmouth.central-southsea.2026-05-07.pdf",
      "sopn_source_url": "https://www.portsmouth.gov.uk/wp-content/uploads/2026/04/Statement-of-Persons-Nominated-2026-City-Council-Elections-accessible-aa.pdf",
      "candidates": [
        {
          "person_id": 123549,
          "name": "Addy ASADUZZAMAN",
          "party_name": "Reform UK",
          "party_ec_id": "PP7931",
          "party_description_text": null,
          "party_list_position": null,
          "deselected": false,
          "elected": null
        },
        {
          "person_id": 131061,
          "name": "Lucy BRIDGEWATER",
          "party_name": "Green Party",
          "party_ec_id": "PP63",
          "party_description_text": null,
          "party_list_position": null,
          "deselected": false,
          "elected": null
        },
        {
          "person_id": 131062,
          "name": "Mackenzie CUMMING",
          "party_name": "Conservative and Unionist Party",
          "party_ec_id": "PP52",
          "party_description_text": "Conservative Party Candidate",
          "party_list_position": null,
          "deselected": false,
          "elected": null
        },
        {
          "person_id": 131063,
          "name": "Kate DORRINGTON",
          "party_name": "Liberal Democrats",
          "party_ec_id": "PP90",
          "party_description_text": "Liberal Democrat",
          "party_list_position": null,
          "deselected": false,
          "elected": null
        },
        {
          "person_id": 39192,
          "name": "George David FIELDING",
          "party_name": "Labour Party",
          "party_ec_id": "PP53",
          "party_description_text": null,
          "party_list_position": null,
          "deselected": false,
          "elected": null
        }
      ]
    },
    {
      "ballot_paper_id": "local.portsmouth.charles-dickens.2026-05-07",
      "post": {
        "id": "gss:E05002443",
        "label": "Charles Dickens",
        "slug": "charles-dickens",
        "created": "2016-03-18T17:09:45.928762Z",
        "last_updated": "2021-10-28T15:44:34.130642+01:00"
      },
      "winner_count": 1,
      "cancelled": false,
      "candidates_locked": true,
      "sopn_url": "https://candidates.democracyclub.org.uk/media/official_documents/local.portsmouth.charles-dickens.2026-05-07/sopn/2026-04-10T09%3A32%3A01.694001%2B00%3A00/sopn-local.portsmouth.charles-dickens.2026-05-07.pdf",
      "sopn_source_url": "https://www.portsmouth.gov.uk/wp-content/uploads/2026/04/Statement-of-Persons-Nominated-2026-City-Council-Elections-accessible-aa.pdf",
      "candidates": [
        {
          "person_id": 88984,
          "name": "Yinka ADENIRAN",
          "party_name": "Labour Party",
          "party_ec_id": "PP53",
          "party_description_text": null,
          "party_list_position": null,
          "deselected": false,
          "elected": null
        },
        {
          "person_id": 89009,
          "name": "David Michael CHANDLER",
          "party_name": "Conservative and Unionist Party",
          "party_ec_id": "PP52",
          "party_description_text": "The Conservative Party Candidate",
          "party_list_position": null,
          "deselected": false,
          "elected": null
        },
        {
          "person_id": 131076,
          "name": "Sam COUPLAND",
          "party_name": "Reform UK",
          "party_ec_id": "PP7931",
          "party_description_text": null,
          "party_list_position": null,
          "deselected": false,
          "elected": null
        },
        {
          "person_id": 82708,
          "name": "Elliott LEE",
          "party_name": "Green Party",
          "party_ec_id": "PP63",
          "party_description_text": null,
          "party_list_position": null,
          "deselected": false,
          "elected": null
        },
        {
          "person_id": 131077,
          "name": "Harold MCGREGOR-SIMS",
          "party_name": "Liberal Democrats",
          "party_ec_id": "PP90",
          "party_description_text": "Liberal Democrat",
          "party_list_position": null,
          "deselected": false,
          "elected": null
        }
      ]
    },
    {
      "ballot_paper_id": "local.portsmouth.copnor.2026-05-07",
      "post": {
        "id": "gss:E05002444",
        "label": "Copnor",
        "slug": "copnor",
        "created": "2016-03-18T17:09:45.952289Z",
        "last_updated": "2021-10-28T15:44:34.177942+01:00"
      },
      "winner_count": 1,
      "cancelled": false,
      "candidates_locked": true,
      "sopn_url": "https://candidates.democracyclub.org.uk/media/official_documents/local.portsmouth.copnor.2026-05-07/sopn/2026-04-10T09%3A32%3A05.320410%2B00%3A00/sopn-local.portsmouth.copnor.2026-05-07.pdf",
      "sopn_source_url": "https://www.portsmouth.gov.uk/wp-content/uploads/2026/04/Statement-of-Persons-Nominated-2026-City-Council-Elections-accessible-aa.pdf",
      "candidates": [
        {
          "person_id": 112321,
          "name": "Andy BUTTERWORTH",
          "party_name": "Labour Party",
          "party_ec_id": "PP53",
          "party_description_text": null,
          "party_list_position": null,
          "deselected": false,
          "elected": null
        },
        {
          "person_id": 38018,
          "name": "Tamara GROEN",
          "party_name": "Green Party",
          "party_ec_id": "PP63",
          "party_description_text": null,
          "party_list_position": null,
          "deselected": false,
          "elected": null
        },
        {
          "person_id": 131080,
          "name": "Carl INMAN",
          "party_name": "Reform UK",
          "party_ec_id": "PP7931",
          "party_description_text": null,
          "party_list_position": null,
          "deselected": false,
          "elected": null
        },
        {
          "person_id": 131081,
          "name": "Paul Antony OAKLEY-CLEIFE",
          "party_name": "Liberal Democrats",
          "party_ec_id": "PP90",
          "party_description_text": "Liberal Democrat",
          "party_list_position": null,
          "deselected": false,
          "elected": null
        },
        {
          "person_id": 17793,
          "name": "Ben SWANN",
          "party_name": "Conservative and Unionist Party",
          "party_ec_id": "PP52",
          "party_description_text": "Local Conservatives",
          "party_list_position": null,
          "deselected": false,
          "elected": null
        }
      ]
    },
    {
      "ballot_paper_id": "local.portsmouth.cosham.2026-05-07",
      "post": {
        "id": "gss:E05002445",
        "label": "Cosham",
        "slug": "cosham",
        "created": "2016-03-18T17:09:45.975781Z",
        "last_updated": "2021-10-28T15:44:34.233257+01:00"
      },
      "winner_count": 1,
      "cancelled": false,
      "candidates_locked": true,
      "sopn_url": "https://candidates.democracyclub.org.uk/media/official_documents/local.portsmouth.cosham.2026-05-07/sopn/2026-04-10T09%3A32%3A05.815643%2B00%3A00/sopn-local.portsmouth.cosham.2026-05-07.pdf",
      "sopn_source_url": "https://www.portsmouth.gov.uk/wp-content/uploads/2026/04/Statement-of-Persons-Nominated-2026-City-Council-Elections-accessible-aa.pdf",
      "candidates": [
        {
          "person_id": 123548,
          "name": "Lamara Louise FUDGE",
          "party_name": "Reform UK",
          "party_ec_id": "PP7931",
          "party_description_text": null,
          "party_list_position": null,
          "deselected": false,
          "elected": null
        },
        {
          "person_id": 131086,
          "name": "Alex DE OLIVEIRA MARTINS",
          "party_name": "Green Party",
          "party_ec_id": "PP63",
          "party_description_text": null,
          "party_list_position": null,
          "deselected": false,
          "elected": null
        },
        {
          "person_id": 82672,
          "name": "Asghar SHAH",
          "party_name": "Labour Party",
          "party_ec_id": "PP53",
          "party_description_text": null,
          "party_list_position": null,
          "deselected": false,
          "elected": null
        },
        {
          "person_id": 131087,
          "name": "Timothy Charles SUFFOLK",
          "party_name": "Liberal Democrats",
          "party_ec_id": "PP90",
          "party_description_text": "Liberal Democrat",
          "party_list_position": null,
          "deselected": false,
          "elected": null
        }
      ]
    },
    {
      "ballot_paper_id": "local.portsmouth.drayton-and-farlington.2026-05-07",
      "post": {
        "id": "gss:E05002446",
        "label": "Drayton and Farlington",
        "slug": "drayton-and-farlington",
        "created": "2016-03-18T17:09:46.001555Z",
        "last_updated": "2021-10-28T15:44:34.283027+01:00"
      },
      "winner_count": 1,
      "cancelled": false,
      "candidates_locked": true,
      "sopn_url": "https://candidates.democracyclub.org.uk/media/official_documents/local.portsmouth.drayton-and-farlington.2026-05-07/sopn/2026-04-10T09%3A32%3A06.412217%2B00%3A00/sopn-local.portsmouth.drayton-and-farlington.2026-05-07.pdf",
      "sopn_source_url": "https://www.portsmouth.gov.uk/wp-content/uploads/2026/04/Statement-of-Persons-Nominated-2026-City-Council-Elections-accessible-aa.pdf",
      "candidates": [
        {
          "person_id": 46321,
          "name": "Simon John BOSHER",
          "party_name": "Conservative and Unionist Party",
          "party_ec_id": "PP52",
          "party_description_text": "Local Conservatives",
          "party_list_position": null,
          "deselected": false,
          "elected": null
        },
        {
          "person_id": 131090,
          "name": "Stephen Michael BURT",
          "party_name": "Reform UK",
          "party_ec_id": "PP7931",
          "party_description_text": null,
          "party_list_position": null,
          "deselected": false,
          "elected": null
        },
        {
          "person_id": 131091,
          "name": "Samantha DARRAGH",
          "party_name": "Liberal Democrats",
          "party_ec_id": "PP90",
          "party_description_text": "Liberal Democrat",
          "party_list_position": null,
          "deselected": false,
          "elected": null
        },
        {
          "person_id": 131092,
          "name": "Matthew Sean HOLLAND",
          "party_name": "Labour Party",
          "party_ec_id": "PP53",
          "party_description_text": null,
          "party_list_position": null,
          "deselected": false,
          "elected": null
        },
        {
          "person_id": 131093,
          "name": "Quenton James KELLEY",
          "party_name": "Green Party",
          "party_ec_id": "PP63",
          "party_description_text": null,
          "party_list_position": null,
          "deselected": false,
          "elected": null
        }
      ]
    },
    {
      "ballot_paper_id": "local.portsmouth.eastney-and-craneswater.2026-05-07",
      "post": {
        "id": "gss:E05002447",
        "label": "Eastney and Craneswater",
        "slug": "eastney-and-craneswater",
        "created": "2018-02-08T11:09:24.314870Z",
        "last_updated": "2021-10-28T15:44:34.333370+01:00"
      },
      "winner_count": 1,
      "cancelled": false,
      "candidates_locked": true,
      "sopn_url": "https://candidates.democracyclub.org.uk/media/official_documents/local.portsmouth.eastney-and-craneswater.2026-05-07/sopn/2026-04-10T09%3A32%3A06.848849%2B00%3A00/sopn-local.portsmouth.eastney-and-craneswater.2026-05-07.pdf",
      "sopn_source_url": "https://www.portsmouth.gov.uk/wp-content/uploads/2026/04/Statement-of-Persons-Nominated-2026-City-Council-Elections-accessible-aa.pdf",
      "candidates": [
        {
          "person_id": 131101,
          "name": "John Malcolm HILL",
          "party_name": "Reform UK",
          "party_ec_id": "PP7931",
          "party_description_text": null,
          "party_list_position": null,
          "deselected": false,
          "elected": null
        },
        {
          "person_id": 112310,
          "name": "Alison Jane HOARE",
          "party_name": "Conservative and Unionist Party",
          "party_ec_id": "PP52",
          "party_description_text": "The Conservative Party Candidate",
          "party_list_position": null,
          "deselected": false,
          "elected": null
        },
        {
          "person_id": 112347,
          "name": "Patrick Charles KEEFE",
          "party_name": "Labour Party",
          "party_ec_id": "PP53",
          "party_description_text": null,
          "party_list_position": null,
          "deselected": false,
          "elected": null
        },
        {
          "person_id": 131102,
          "name": "Cliff PARSONS",
          "party_name": "Heritage Party",
          "party_ec_id": "PP12550",
          "party_description_text": null,
          "party_list_position": null,
          "deselected": false,
          "elected": null
        },
        {
          "person_id": 131103,
          "name": "Lizzie ROSE",
          "party_name": "Green Party",
          "party_ec_id": "PP63",
          "party_description_text": null,
          "party_list_position": null,
          "deselected": false,
          "elected": null
        },
        {
          "person_id": 6440,
          "name": "Matthew Ray WINNINGTON",
          "party_name": "Liberal Democrats",
          "party_ec_id": "PP90",
          "party_description_text": "Liberal Democrat",
          "party_list_position": null,
          "deselected": false,
          "elected": null
        }
      ]
    },
    {
      "ballot_paper_id": "local.portsmouth.fratton.2026-05-07",
      "post": {
        "id": "gss:E05002448",
        "label": "Fratton",
        "slug": "fratton",
        "created": "2016-03-18T17:09:46.048088Z",
        "last_updated": "2021-10-28T15:44:34.383128+01:00"
      },
      "winner_count": 1,
      "cancelled": false,
      "candidates_locked": true,
      "sopn_url": "https://candidates.democracyclub.org.uk/media/official_documents/local.portsmouth.fratton.2026-05-07/sopn/2026-04-10T09%3A32%3A07.369827%2B00%3A00/sopn-local.portsmouth.fratton.2026-05-07.pdf",
      "sopn_source_url": "https://www.portsmouth.gov.uk/wp-content/uploads/2026/04/Statement-of-Persons-Nominated-2026-City-Council-Elections-accessible-aa.pdf",
      "candidates": [
        {
          "person_id": 131105,
          "name": "Billy Ansell",
          "party_name": "Liberal Democrats",
          "party_ec_id": "PP90",
          "party_description_text": "Liberal Democrat",
          "party_list_position": null,
          "deselected": false,
          "elected": null
        },
        {
          "person_id": 46260,
          "name": "Tom Coles",
          "party_name": "Labour Party",
          "party_ec_id": "PP53",
          "party_description_text": null,
          "party_list_position": null,
          "deselected": false,
          "elected": null
        },
        {
          "person_id": 112298,
          "name": "Tim Edwards",
          "party_name": "Conservative and Unionist Party",
          "party_ec_id": "PP52",
          "party_description_text": "Conservative Party Candidate",
          "party_list_position": null,
          "deselected": false,
          "elected": null
        },
        {
          "person_id": 38014,
          "name": "Tim Sheerman-Chase",
          "party_name": "Green Party",
          "party_ec_id": "PP63",
          "party_description_text": "The Green Party candidate",
          "party_list_position": null,
          "deselected": false,
          "elected": null
        },
        {
          "person_id": 102289,
          "name": "Jacob Lee Short",
          "party_name": "Reform UK",
          "party_ec_id": "PP7931",
          "party_description_text": null,
          "party_list_position": null,
          "deselected": false,
          "elected": null
        }
      ]
    },
    {
      "ballot_paper_id": "local.portsmouth.hilsea.2026-05-07",
      "post": {
        "id": "gss:E05002449",
        "label": "Hilsea",
        "slug": "hilsea",
        "created": "2016-03-18T17:09:46.074024Z",
        "last_updated": "2021-10-28T15:44:34.432994+01:00"
      },
      "winner_count": 1,
      "cancelled": false,
      "candidates_locked": true,
      "sopn_url": "https://candidates.democracyclub.org.uk/media/official_documents/local.portsmouth.hilsea.2026-05-07/sopn/2026-04-10T09%3A32%3A08.023933%2B00%3A00/sopn-local.portsmouth.hilsea.2026-05-07.pdf",
      "sopn_source_url": "https://www.portsmouth.gov.uk/wp-content/uploads/2026/04/Statement-of-Persons-Nominated-2026-City-Council-Elections-accessible-aa.pdf",
      "candidates": [
        {
          "person_id": 6221,
          "name": "Matthew Jeremy ATKINS",
          "party_name": "Conservative and Unionist Party",
          "party_ec_id": "PP52",
          "party_description_text": "The Conservative Party Candidate",
          "party_list_position": null,
          "deselected": false,
          "elected": null
        },
        {
          "person_id": 101681,
          "name": "Edward BATTERBURY",
          "party_name": "Labour Party",
          "party_ec_id": "PP53",
          "party_description_text": null,
          "party_list_position": null,
          "deselected": false,
          "elected": null
        },
        {
          "person_id": 38017,
          "name": "Emma Louise Kimberley MURPHY",
          "party_name": "Green Party",
          "party_ec_id": "PP63",
          "party_description_text": null,
          "party_list_position": null,
          "deselected": false,
          "elected": null
        },
        {
          "person_id": 93921,
          "name": "Russell Peter William SIMPSON",
          "party_name": "Reform UK",
          "party_ec_id": "PP7931",
          "party_description_text": null,
          "party_list_position": null,
          "deselected": false,
          "elected": null
        },
        {
          "person_id": 131123,
          "name": "Kristine TEIVANE",
          "party_name": "Liberal Democrats",
          "party_ec_id": "PP90",
          "party_description_text": "Liberal Democrat",
          "party_list_position": null,
          "deselected": false,
          "elected": null
        }
      ]
    },
    {
      "ballot_paper_id": "local.portsmouth.milton.2026-05-07",
      "post": {
        "id": "gss:E05002450",
        "label": "Milton",
        "slug": "milton",
        "created": "2016-03-18T17:09:46.097414Z",
        "last_updated": "2021-10-28T15:44:34.482734+01:00"
      },
      "winner_count": 1,
      "cancelled": false,
      "candidates_locked": true,
      "sopn_url": "https://candidates.democracyclub.org.uk/media/official_documents/local.portsmouth.milton.2026-05-07/sopn/2026-04-10T09%3A32%3A08.535372%2B00%3A00/sopn-local.portsmouth.milton.2026-05-07.pdf",
      "sopn_source_url": "https://www.portsmouth.gov.uk/wp-content/uploads/2026/04/Statement-of-Persons-Nominated-2026-City-Council-Elections-accessible-aa.pdf",
      "candidates": [
        {
          "person_id": 131126,
          "name": "Perry BARTER",
          "party_name": "Independent",
          "party_ec_id": "ynmp-party:2",
          "party_description_text": null,
          "party_list_position": null,
          "deselected": false,
          "elected": null
        },
        {
          "person_id": 131127,
          "name": "Phil CARPENTER",
          "party_name": "Reform UK",
          "party_ec_id": "PP7931",
          "party_description_text": null,
          "party_list_position": null,
          "deselected": false,
          "elected": null
        },
        {
          "person_id": 131128,
          "name": "Melinda KOLLER",
          "party_name": "Conservative and Unionist Party",
          "party_ec_id": "PP52",
          "party_description_text": "Conservative Party Candidate",
          "party_list_position": null,
          "deselected": false,
          "elected": null
        },
        {
          "person_id": 17731,
          "name": "Steve PITT",
          "party_name": "Liberal Democrats",
          "party_ec_id": "PP90",
          "party_description_text": "Liberal Democrat",
          "party_list_position": null,
          "deselected": false,
          "elected": null
        },
        {
          "person_id": 61012,
          "name": "Paula Ann SAVAGE",
          "party_name": "Green Party",
          "party_ec_id": "PP63",
          "party_description_text": null,
          "party_list_position": null,
          "deselected": false,
          "elected": null
        },
        {
          "person_id": 131130,
          "name": "David Richard TRACE",
          "party_name": "Labour Party",
          "party_ec_id": "PP53",
          "party_description_text": null,
          "party_list_position": null,
          "deselected": false,
          "elected": null
        }
      ]
    },
    {
      "ballot_paper_id": "local.portsmouth.nelson.2026-05-07",
      "post": {
        "id": "gss:E05002451",
        "label": "Nelson",
        "slug": "nelson",
        "created": "2016-03-18T17:09:46.122521Z",
        "last_updated": "2021-10-28T15:44:34.537832+01:00"
      },
      "winner_count": 1,
      "cancelled": false,
      "candidates_locked": true,
      "sopn_url": "https://candidates.democracyclub.org.uk/media/official_documents/local.portsmouth.nelson.2026-05-07/sopn/2026-04-10T09%3A32%3A08.975978%2B00%3A00/sopn-local.portsmouth.nelson.2026-05-07.pdf",
      "sopn_source_url": "https://www.portsmouth.gov.uk/wp-content/uploads/2026/04/Statement-of-Persons-Nominated-2026-City-Council-Elections-accessible-aa.pdf",
      "candidates": [
        {
          "person_id": 131132,
          "name": "Steve ANDREWS",
          "party_name": "Liberal Democrats",
          "party_ec_id": "PP90",
          "party_description_text": "Liberal Democrat",
          "party_list_position": null,
          "deselected": false,
          "elected": null
        },
        {
          "person_id": 36459,
          "name": "Jason FAZACKARLEY",
          "party_name": "Reform UK",
          "party_ec_id": "PP7931",
          "party_description_text": null,
          "party_list_position": null,
          "deselected": false,
          "elected": null
        },
        {
          "person_id": 61018,
          "name": "Lewis Mark David GOSLING",
          "party_name": "Conservative and Unionist Party",
          "party_ec_id": "PP52",
          "party_description_text": "Local Conservatives",
          "party_list_position": null,
          "deselected": false,
          "elected": null
        },
        {
          "person_id": 102309,
          "name": "Robin HEAD",
          "party_name": "Labour Party",
          "party_ec_id": "PP53",
          "party_description_text": null,
          "party_list_position": null,
          "deselected": false,
          "elected": null
        },
        {
          "person_id": 131133,
          "name": "Stan MARLOW",
          "party_name": "Green Party",
          "party_ec_id": "PP63",
          "party_description_text": null,
          "party_list_position": null,
          "deselected": false,
          "elected": null
        }
      ]
    },
    {
      "ballot_paper_id": "local.portsmouth.paulsgrove.2026-05-07",
      "post": {
        "id": "gss:E05002452",
        "label": "Paulsgrove",
        "slug": "paulsgrove",
        "created": "2016-03-18T17:09:46.150007Z",
        "last_updated": "2021-10-28T15:44:34.586552+01:00"
      },
      "winner_count": 1,
      "cancelled": false,
      "candidates_locked": true,
      "sopn_url": "https://candidates.democracyclub.org.uk/media/official_documents/local.portsmouth.paulsgrove.2026-05-07/sopn/2026-04-10T09%3A32%3A09.447996%2B00%3A00/sopn-local.portsmouth.paulsgrove.2026-05-07.pdf",
      "sopn_source_url": "https://www.portsmouth.gov.uk/wp-content/uploads/2026/04/Statement-of-Persons-Nominated-2026-City-Council-Elections-accessible-aa.pdf",
      "candidates": [
        {
          "person_id": 5875,
          "name": "Mark Andrew FARWELL",
          "party_name": "Labour Party",
          "party_ec_id": "PP53",
          "party_description_text": null,
          "party_list_position": null,
          "deselected": false,
          "elected": null
        },
        {
          "person_id": 112346,
          "name": "Thomas Christopher HOARE",
          "party_name": "Conservative and Unionist Party",
          "party_ec_id": "PP52",
          "party_description_text": "Local Conservatives",
          "party_list_position": null,
          "deselected": false,
          "elected": null
        },
        {
          "person_id": 4643,
          "name": "Ian David MCCULLOCH",
          "party_name": "Green Party",
          "party_ec_id": "PP63",
          "party_description_text": null,
          "party_list_position": null,
          "deselected": false,
          "elected": null
        },
        {
          "person_id": 123206,
          "name": "Michelle Jenny SIMMONS",
          "party_name": "Liberal Democrats",
          "party_ec_id": "PP90",
          "party_description_text": "Liberal Democrat",
          "party_list_position": null,
          "deselected": false,
          "elected": null
        },
        {
          "person_id": 101714,
          "name": "Joe STANDEN",
          "party_name": "Reform UK",
          "party_ec_id": "PP7931",
          "party_description_text": null,
          "party_list_position": null,
          "deselected": false,
          "elected": null
        }
      ]
    },
    {
      "ballot_paper_id": "local.portsmouth.st-jude.2026-05-07",
      "post": {
        "id": "gss:E05002453",
        "label": "St Jude",
        "slug": "st-jude",
        "created": "2016-03-18T17:09:46.176022Z",
        "last_updated": "2021-10-28T15:44:34.636153+01:00"
      },
      "winner_count": 1,
      "cancelled": false,
      "candidates_locked": true,
      "sopn_url": "https://candidates.democracyclub.org.uk/media/official_documents/local.portsmouth.st-jude.2026-05-07/sopn/2026-04-10T09%3A32%3A09.998812%2B00%3A00/sopn-local.portsmouth.st-jude.2026-05-07.pdf",
      "sopn_source_url": "https://www.portsmouth.gov.uk/wp-content/uploads/2026/04/Statement-of-Persons-Nominated-2026-City-Council-Elections-accessible-aa.pdf",
      "candidates": [
        {
          "person_id": 131144,
          "name": "Alvie Syed Ihsan MAHMUD",
          "party_name": "Green Party",
          "party_ec_id": "PP63",
          "party_description_text": null,
          "party_list_position": null,
          "deselected": false,
          "elected": null
        },
        {
          "person_id": 131145,
          "name": "Mitchell NEWMAN",
          "party_name": "Reform UK",
          "party_ec_id": "PP7931",
          "party_description_text": null,
          "party_list_position": null,
          "deselected": false,
          "elected": null
        },
        {
          "person_id": 131146,
          "name": "Denise PERRY",
          "party_name": "Liberal Democrats",
          "party_ec_id": "PP90",
          "party_description_text": "Liberal Democrat",
          "party_list_position": null,
          "deselected": false,
          "elected": null
        },
        {
          "person_id": 131147,
          "name": "Orsolya POKOLY",
          "party_name": "Conservative and Unionist Party",
          "party_ec_id": "PP52",
          "party_description_text": "Conservative Party Candidate",
          "party_list_position": null,
          "deselected": false,
          "elected": null
        },
        {
          "person_id": 46313,
          "name": "Judith Deborah SMYTH",
          "party_name": "Labour Party",
          "party_ec_id": "PP53",
          "party_description_text": null,
          "party_list_position": null,
          "deselected": false,
          "elected": null
        }
      ]
    },
    {
      "ballot_paper_id": "local.portsmouth.st-thomas.2026-05-07",
      "post": {
        "id": "gss:E05002454",
        "label": "St Thomas",
        "slug": "st-thomas",
        "created": "2016-03-18T17:09:46.198815Z",
        "last_updated": "2021-10-28T15:44:34.687124+01:00"
      },
      "winner_count": 1,
      "cancelled": false,
      "candidates_locked": true,
      "sopn_url": "https://candidates.democracyclub.org.uk/media/official_documents/local.portsmouth.st-thomas.2026-05-07/sopn/2026-04-10T09%3A32%3A10.804993%2B00%3A00/sopn-local.portsmouth.st-thomas.2026-05-07.pdf",
      "sopn_source_url": "https://www.portsmouth.gov.uk/wp-content/uploads/2026/04/Statement-of-Persons-Nominated-2026-City-Council-Elections-accessible-aa.pdf",
      "candidates": [
        {
          "person_id": 131150,
          "name": "Tom AUSTIN",
          "party_name": "Labour Party",
          "party_ec_id": "PP53",
          "party_description_text": null,
          "party_list_position": null,
          "deselected": false,
          "elected": null
        },
        {
          "person_id": 46276,
          "name": "Terry HENDERSON",
          "party_name": "Conservative and Unionist Party",
          "party_ec_id": "PP52",
          "party_description_text": "Conservative Party Candidate",
          "party_list_position": null,
          "deselected": false,
          "elected": null
        },
        {
          "person_id": 89017,
          "name": "Mark JEFFERY",
          "party_name": "Liberal Democrats",
          "party_ec_id": "PP90",
          "party_description_text": "Liberal Democrat",
          "party_list_position": null,
          "deselected": false,
          "elected": null
        },
        {
          "person_id": 131151,
          "name": "Jay MERCER",
          "party_name": "Green Party",
          "party_ec_id": "PP63",
          "party_description_text": null,
          "party_list_position": null,
          "deselected": false,
          "elected": null
        },
        {
          "person_id": 131152,
          "name": "Oskar Lucjan ZABICKI",
          "party_name": "Reform UK",
          "party_ec_id": "PP7931",
          "party_description_text": null,
          "party_list_position": null,
          "deselected": false,
          "elected": null
        }
      ]
    }
  ]
}